HISTORY.md
MANIFEST.in
README.md
requirements.txt
setup.cfg
setup.py
src/umls_api/__init__.py
src/umls_api/api.py
src/umls_api.egg-info/PKG-INFO
src/umls_api.egg-info/SOURCES.txt
src/umls_api.egg-info/dependency_links.txt
src/umls_api.egg-info/not-zip-safe
src/umls_api.egg-info/requires.txt
src/umls_api.egg-info/top_level.txt