Metadata-Version: 2.1
Name: umls-api
Version: 0.1.0
Summary: UNKNOWN
Home-page: https://github.com/odwyersoftware/umls-api
Author: O'Dwyer Software
Author-email: hello@odwyer.software
License: Apache 2
Platform: UNKNOWN
Classifier: Intended Audience :: Developers
Classifier: Operating System :: OS Independent
Classifier: Programming Language :: Python
Classifier: Programming Language :: Python :: 3
Classifier: Topic :: Internet :: WWW/HTTP
